fastmvc/__init__.py
fastmvc/extras/flickr.py
fastmvc/generator.py
fastmvc/main.py
fastmvc/models/database/_base.py
fastmvc/models/database/deta.py
fastmvc/models/database/firestore.py
fastmvc/models/html.py
fastmvc/templates/core/.env
fastmvc/templates/core/.gitignore
fastmvc/templates/core/app.yaml
fastmvc/templates/core/ignore/service-account-file.json
fastmvc/templates/core/main.py
fastmvc/templates/core/requirements.txt
fastmvc/templates/core/static_pages/router.py
fastmvc/templates/core/static_pages/static/css/core.css
fastmvc/templates/core/static_pages/static/css/stylesheet.css
fastmvc/templates/core/static_pages/static/img/logo.svg
fastmvc/templates/core/static_pages/static/js/application.js
fastmvc/templates/core/static_pages/static/js/color-modes.js
fastmvc/templates/core/static_pages/templates/_base.html
fastmvc/templates/core/static_pages/templates/_color_mode.html
fastmvc/templates/core/static_pages/templates/_navlinks.html
fastmvc/templates/core/static_pages/templates/_svg_symbols.html
fastmvc/templates/core/static_pages/templates/index.html
fastmvc/templates/scaffold/model.py
fastmvc/templates/scaffold/router.py
fastmvc/templates/scaffold/templates/form.html
fastmvc/templates/scaffold/templates/index.html
fastmvc/templates/scaffold/templates/view.html
fastmvc/templates/scaffold_helpers/bool.html
fastmvc/templates/scaffold_helpers/float.html
fastmvc/templates/scaffold_helpers/int.html
fastmvc/templates/scaffold_helpers/reference_model_list.py
fastmvc/templates/scaffold_helpers/scaffold_navlink.html
fastmvc/templates/scaffold_helpers/str.html
fastmvc/templates/scaffold_helpers/text.html
fastmvc/templates/scaffold_helpers/trix_meta_content.html
fastmvc/templates/scaffold_helpers/user_login.html
fastmvc/templates/scaffold_helpers/wysiwyg.html
fastmvc/templates/simple_auth/model.py
fastmvc/templates/simple_auth/router.py
fastmvc/templates/simple_auth/templates/dashboard.html
fastmvc/templates/simple_auth/templates/login.html
fastmvc-0.1.7.dist-info/entry_points.txt
fastmvc-0.1.7.dist-info/LICENSE
fastmvc-0.1.7.dist-info/METADATA
fastmvc-0.1.7.dist-info/WHEEL
fastmvc-0.1.7.dist-info/RECORD
