Metadata-Version: 2.1
Name: fastmvc
Version: 0.1.7
Summary: Rapid application development built for the cloud.
Home-page: https://github.com/pyn-sol/FastMVC
Author: MBeebe
Author-email: pyn-sol@beebe.dev
Requires-Python: >=3.7
Classifier: Programming Language :: Python :: 3
Classifier: Programming Language :: Python :: 3.7
Classifier: Programming Language :: Python :: 3.8
Classifier: Programming Language :: Python :: 3.9
Classifier: Programming Language :: Python :: 3.10
Classifier: Programming Language :: Python :: 3.11
Requires-Dist: Jinja2
Requires-Dist: authlib
Requires-Dist: fastapi
Requires-Dist: httpx
Requires-Dist: itsdangerous
Requires-Dist: passlib[bcrypt]
Requires-Dist: pyjwt
Requires-Dist: python-dotenv
Requires-Dist: python-multipart
Requires-Dist: typer[all]
Project-URL: Repository, https://github.com/pyn-sol/FastMVC
